quickerml/__init__.py
quickerml/exceptions.py
quickerml/finder.py
quickerml/metrics.py
quickerml-0.1.0.dist-info/METADATA
quickerml-0.1.0.dist-info/WHEEL
quickerml-0.1.0.dist-info/top_level.txt
quickerml-0.1.0.dist-info/RECORD
