Metadata-Version: 2.1
Name: quickerml
Version: 0.1.0
Summary: Machine learning toolkit to find the best starting model for your project
Home-page: https://quickerml.readthedocs.io/
Author: Rafael Moret
Author-email: rafaelmoretgalan@gmail.com
License: MIT
Platform: UNKNOWN
Classifier: Intended Audience :: Developers
Classifier: License :: OSI Approved :: MIT License
Classifier: Programming Language :: Python
Classifier: Programming Language :: Python :: 3
Classifier: Programming Language :: Python :: 3.6
Classifier: Programming Language :: Python :: 3.7
Classifier: Programming Language :: Python :: 3.8
Classifier: Programming Language :: Python :: 3.9
Classifier: Programming Language :: Python :: 3.10
Classifier: Operating System :: OS Independent
Requires-Dist: pandas
Requires-Dist: numpy
Requires-Dist: tqdm
Requires-Dist: catboost
Requires-Dist: lightgbm
Requires-Dist: xgboost
Requires-Dist: scikit-learn
